tuto_control_lib/__init__.py
tuto_control_lib/plot.py
tuto_control_lib/systems.py
tuto_control_lib/utils.py
tuto_control_lib/cigri/__init__.py
tuto_control_lib/cigri/cigri.py
tuto_control_lib/cigri/events.py
tuto_control_lib/cigri/jobs.py
tuto_control_lib/cigri/oar.py
tuto_control_lib-1.3.1.dist-info/LICENSE
tuto_control_lib-1.3.1.dist-info/METADATA
tuto_control_lib-1.3.1.dist-info/WHEEL
tuto_control_lib-1.3.1.dist-info/top_level.txt
tuto_control_lib-1.3.1.dist-info/RECORD
